{
    "ItemFeedHeader": {
        "sellingChannel": "precisedelivery",
        "locale": "en",
        "version": "1.0"
    },
    "Item": [
        {
            "PreciseDelivery": {
                "sku": "Automation1753411575148",
                "actionType": "Add",
                "shippingTemplateId": "2024031999000003884",
                "fulfillmentCenterId": "571946440100757506"
            }
        },
        {
            "PreciseDelivery": {
                "sku": "Automation1753411575148",
                "actionType": "Remove",
                "shippingTemplateId": "439650814676398081",
                "fulfillmentCenterId": "571946440100757501"
            }
        }
    ]
}